abao_ai/__init__.py
abao_ai/discord_bot.py
abao_ai/engine.py
abao_ai/flux.py
abao_ai/info.py
abao_ai/install.py
abao_ai/main.py
abao_ai/parser.py
abao_ai/shared_dir.py
abao_ai/util.py
abao_ai-0.0.5.dist-info/METADATA
abao_ai-0.0.5.dist-info/WHEEL
abao_ai-0.0.5.dist-info/entry_points.txt
abao_ai-0.0.5.dist-info/top_level.txt
abao_ai-0.0.5.dist-info/RECORD
