Metadata-Version: 2.4
Name: abao_ai
Version: 0.0.5
Summary: abao.ai discord bot
Author-email: Yinchu Xia <sales@pytorchsoft.com>
Project-URL: Homepage, https://github.com/pytorchsoft/abao_ai
Project-URL: Issues, https://github.com/pytorchsoft/abao_ai/issues
Classifier: Programming Language :: Python :: 3
Classifier: Operating System :: POSIX :: Linux
Requires-Python: >=3.9
Requires-Dist: ray
Requires-Dist: sentencepiece
Requires-Dist: transformers
Requires-Dist: einops
Requires-Dist: colored
Requires-Dist: onnx
Requires-Dist: polygraphy
Requires-Dist: tensorrt
Requires-Dist: huggingface_hub[cli]
Requires-Dist: pyyaml
Requires-Dist: psutil
Requires-Dist: cuda-python
Requires-Dist: discord.py
Requires-Dist: torch
Requires-Dist: torchvision
Requires-Dist: torchaudio
